MANIFEST.in
setup.py
election_parser/__init__.py
election_parser/exceptions.py
election_parser/formatter.py
election_parser/loader.py
election_parser/server.py
election_parser/states.py
election_parser/utils.py
election_parser/xml_parser.py
election_parser.egg-info/PKG-INFO
election_parser.egg-info/SOURCES.txt
election_parser.egg-info/dependency_links.txt
election_parser.egg-info/requires.txt
election_parser.egg-info/top_level.txt
election_parser/test/__init__.py
election_parser/test/live_server.py
election_parser/test/data/ca/00000001-X12PG.zip
election_parser/test/data/ca/00000002-X12PG.zip
election_parser/test/data/ca/00000003-X12PG.zip
election_parser/test/data/ca/00000004-X12PG.zip
election_parser/test/data/ca/00000005-X12PG.zip
election_parser/test/data/ca/00000006-X12PG.zip
election_parser/test/data/ca/00000007-X12PG.zip
election_parser/test/data/ca/00000008-X12PG.zip
election_parser/test/data/ca/00000009-X12PG.zip
election_parser/test/data/ca/00000010-X12PG.zip
election_parser/test/data/ca/00000011-X12PG.zip
election_parser/test/data/ca/00000012-X12PG.zip
election_parser/test/data/ca/00000013-X12PG.zip
election_parser/test/data/ca/00000014-X12PG.zip
election_parser/test/data/ca/00000015-X12PG.zip
election_parser/test/data/ca/00000016-X12PG.zip
election_parser/test/data/ca/00000017-X12PG.zip
election_parser/test/data/ca/00000018-X12PG.zip
election_parser/test/data/ca/00000019-X12PG.zip
election_parser/test/data/ca/00000020-X12PG.zip
election_parser/test/data/ca/00000021-X12PG.zip
election_parser/test/data/ca/00000022-X12PG.zip
election_parser/test/data/ca/00000023-X12PG.zip
election_parser/test/data/ca/00000024-X12PG.zip
election_parser/test/data/ca/00000025-X12PG.zip
election_parser/test/data/ca/00000026-X12PG.zip
election_parser/test/data/ca/00000027-X12PG.zip
election_parser/test/data/ca/00000028-X12PG.zip
election_parser/test/data/ca/00000029-X12PG.zip
election_parser/test/data/ca/00000030-X12PG.zip
election_parser/test/data/ca/00000031-X12PG.zip
election_parser/test/data/ca/00000032-X12PG.zip
election_parser/test/data/ca/00000033-X12PG.zip
election_parser/test/data/fl/09202011Election.txt
election_parser/test/data/va/xml_1109_pre.xml
