Metadata-Version: 1.0
Name: election-parser
Version: 0.0.1
Summary: Parse US real time and archived election data.  Really only supports CA real time rigth now
Home-page: http://github.com/adamdeprince/election_parser
Author: Adam DePrince
Author-email: deprince@googlealumni.com
License: GPLv2
Platform: UNKNOWN
Classifier: Intended Audience :: Developers
